fpga/twi_proxy.v
// Proxies I2C from one set of pins to another. Will introduce a slight
// propagation delay.
module twi_proxy(
		input clk,

		// Host wires (not to be controlled by us)
		input hostScl,
		input hostSdaIn,
		output hostSdaLow,

		// Mirror ports (we're driving these)
		output mirrorScl,
		input mirrorSdaIn,
		output mirrorSdaLow
	);

	reg hostToMirror = 1'b0;
	reg mirrorToHost = 1'b0;
	reg hostRecovery = 1'b0;
	reg mirrorRecovery = 1'b0;

	assign mirrorScl = hostScl;
	
	assign hostSdaLow = mirrorToHost;
	assign mirrorSdaLow = hostToMirror;

	always @* begin
		casez ({hostRecovery,mirrorRecovery,hostSdaIn,mirrorSdaIn,hostToMirror,mirrorToHost})
             	  // Waiting for recovery
		  6'b1?_?1_00: hostRecovery <= 0;
		  6'b?1_1?_00: mirrorRecovery <= 0;
		  // Enabling the mirror
		  6'b00_01_00: {hostToMirror, hostRecovery} <= 2'b11;
		  6'b00_10_00: {mirrorToHost, mirrorRecovery} <= 2'b11;
		  // Disabling the mirror
		  6'b??_1?_1?: hostToMirror <= 0;
		  6'b??_?1_?1: mirrorToHost <= 0;
		endcase
		/*if (!waitForRecovery) begin
			if (!hostSdaIn && !mirrorToHost)
				{hostToMirror, waitForRecovery} <= 2'b11;
			else if (!mirrorSdaIn && !hostToMirror)
				{mirrorToHost, waitForRecovery} <= 2'b11;
		end
		else begin
			if (hostSdaIn && mirrorSdaIn)
				waitForRecovery <= 0;
			if (hostSdaIn)
				hostToMirror <= 1'b0;
			if (mirrorSdaIn)
				mirrorToHost <= 1'b0;
		end;*/
	end
endmodule

fpga/twi_proxy_tb.v
module twi_proxy_tb();
	reg hostScl = 1'b0;
	reg hostSdaWanted = 1'b1;
	wire effectiveHostSda, hostSdaLow;
	assign effectiveHostSda = hostSdaLow ? 1'b0 : hostSdaWanted;

	reg mirrorSdaWanted = 1'b1;
	wire mirrorScl, effectiveMirrorSda, mirrorSdaLow;
	assign effectiveMirrorSda = mirrorSdaLow ? 1'b0 : mirrorSdaWanted;

	twi_proxy INST (
		.hostScl(hostScl),
		.hostSdaIn(effectiveHostSda),
		.hostSdaLow(hostSdaLow),
		.mirrorScl(mirrorScl),
		.mirrorSdaIn(effectiveMirrorSda),
		.mirrorSdaLow(mirrorSdaLow)
	);

	always #1 hostScl <= ~hostScl;

	initial begin
		$dumpfile("twi_proxy_tb.vcd");
		$dumpvars;
		
		#5 hostSdaWanted <= 1'b0;
		#10 hostSdaWanted <= 1'b1;
		
		#20 mirrorSdaWanted <= 1'b0;
		#25 mirrorSdaWanted <= 1'b1;
		
		#30 hostSdaWanted <= 1'b0;
		#35 hostSdaWanted <= 1'b1;

		#40 mirrorSdaWanted <= 1'b0;
		#45 hostSdaWanted <= 1'b0;
		#50 mirrorSdaWanted <= 1'b1;
		#55 hostSdaWanted <= 1'b1;

		#60 $finish;
	end
endmodule

fpga/twi_proxy_tb.vcd
$date
	Wed Jan 23 22:49:21 2019
$end
$version
	Icarus Verilog
$end
$timescale
	1s
$end
$scope module twi_proxy_tb $end
$var wire 1 ! mirrorSdaLow $end
$var wire 1 " mirrorScl $end
$var wire 1 # hostSdaLow $end
$var wire 1 $ effectiveMirrorSda $end
$var wire 1 % effectiveHostSda $end
$var reg 1 & hostScl $end
$var reg 1 ' hostSdaWanted $end
$var reg 1 ( mirrorSdaWanted $end
$scope module INST $end
$var wire 1 ) clk $end
$var wire 1 & hostScl $end
$var wire 1 % hostSdaIn $end
$var wire 1 " mirrorScl $end
$var wire 1 $ mirrorSdaIn $end
$var wire 1 ! mirrorSdaLow $end
$var wire 1 # hostSdaLow $end
$var reg 1 * hostRecovery $end
$var reg 1 ! hostToMirror $end
$var reg 1 + mirrorRecovery $end
$var reg 1 # mirrorToHost $end
$upscope $end
$upscope $end
$enddefinitions $end
#0
$dumpvars
0+
0*
z)
1(
1'
0&
1%
1$
0#
0"
0!
$end
#1
1"
1&
#2
0"
0&
#3
1"
1&
#4
0"
0&
#5
0$
1!
1*
0%
1"
1&
0'
#6
0"
0&
#7
1"
1&
#8
0"
0&
#9
1"
1&
#10
0"
0&
#11
1"
1&
#12
0"
0&
#13
1"
1&
#14
0"
0&
#15
0*
1$
0!
1%
1"
1&
1'
#16
0"
0&
#17
1"
1&
#18
0"
0&
#19
1"
1&
#20
0"
0&
#21
1"
1&
#22
0"
0&
#23
1"
1&
#24
0"
0&
#25
1"
1&
#26
0"
0&
#27
1"
1&
#28
0"
0&
#29
1"
1&
#30
0"
0&
#31
1"
1&
#32
0"
0&
#33
1"
1&
#34
0"
0&
#35
0%
1#
1+
0$
1"
1&
0(
#36
0"
0&
#37
1"
1&
#38
0"
0&
#39
1"
1&
#40
0"
0&
#41
1"
1&
#42
0"
0&
#43
1"
1&
#44
0"
0&
#45
1"
1&
#46
0"
0&
#47
1"
1&
#48
0"
0&
#49
1"
1&
#50
0"
0&
#51
1"
1&
#52
0"
0&
#53
1"
1&
#54
0"
0&
#55
1"
1&
#56
0"
0&
#57
1"
1&
#58
0"
0&
#59
1"
1&
#60
0+
1%
0#
1$
0"
0&
1(
#61
1"
1&
#62
0"
0&
#63
1"
1&
#64
0"
0&
#65
1"
1&
#66
0"
0&
#67
1"
1&
#68
0"
0&
#69
1"
1&
#70
0"
0&
#71
1"
1&
#72
0"
0&
#73
1"
1&
#74
0"
0&
#75
1"
1&
#76
0"
0&
#77
1"
1&
#78
0"
0&
#79
1"
1&
#80
0"
0&
#81
1"
1&
#82
0"
0&
#83
1"
1&
#84
0"
0&
#85
1"
1&
#86
0"
0&
#87
1"
1&
#88
0"
0&
#89
1"
1&
#90
0$
1!
1*
0%
0"
0&
0'
#91
1"
1&
#92
0"
0&
#93
1"
1&
#94
0"
0&
#95
1"
1&
#96
0"
0&
#97
1"
1&
#98
0"
0&
#99
1"
1&
#100
0"
0&
#101
1"
1&
#102
0"
0&
#103
1"
1&
#104
0"
0&
#105
1"
1&
#106
0"
0&
#107
1"
1&
#108
0"
0&
#109
1"
1&
#110
0"
0&
#111
1"
1&
#112
0"
0&
#113
1"
1&
#114
0"
0&
#115
1"
1&
#116
0"
0&
#117
1"
1&
#118
0"
0&
#119
1"
1&
#120
0"
0&
#121
1"
1&
#122
0"
0&
#123
1"
1&
#124
0"
0&
#125
0*
1$
0!
1%
1"
1&
1'
#126
0"
0&
#127
1"
1&
#128
0"
0&
#129
1"
1&
#130
0"
0&
#131
1"
1&
#132
0"
0&
#133
1"
1&
#134
0"
0&
#135
1"
1&
#136
0"
0&
#137
1"
1&
#138
0"
0&
#139
1"
1&
#140
0"
0&
#141
1"
1&
#142
0"
0&
#143
1"
1&
#144
0"
0&
#145
1"
1&
#146
0"
0&
#147
1"
1&
#148
0"
0&
#149
1"
1&
#150
0"
0&
#151
1"
1&
#152
0"
0&
#153
1"
1&
#154
0"
0&
#155
1"
1&
#156
0"
0&
#157
1"
1&
#158
0"
0&
#159
1"
1&
#160
0"
0&
#161
1"
1&
#162
0"
0&
#163
1"
1&
#164
0"
0&
#165
0%
1#
1+
0$
1"
1&
0(
#166
0"
0&
#167
1"
1&
#168
0"
0&
#169
1"
1&
#170
0"
0&
#171
1"
1&
#172
0"
0&
#173
1"
1&
#174
0"
0&
#175
1"
1&
#176
0"
0&
#177
1"
1&
#178
0"
0&
#179
1"
1&
#180
0"
0&
#181
1"
1&
#182
0"
0&
#183
1"
1&
#184
0"
0&
#185
1"
1&
#186
0"
0&
#187
1"
1&
#188
0"
0&
#189
1"
1&
#190
0"
0&
#191
1"
1&
#192
0"
0&
#193
1"
1&
#194
0"
0&
#195
1"
1&
#196
0"
0&
#197
1"
1&
#198
0"
0&
#199
1"
1&
#200
0"
0&
#201
1"
1&
#202
0"
0&
#203
1"
1&
#204
0"
0&
#205
1"
1&
#206
0"
0&
#207
1"
1&
#208
0"
0&
#209
1"
1&
#210
0"
0&
0'
#211
1"
1&
#212
0"
0&
#213
1"
1&
#214
0"
0&
#215
1"
1&
#216
0"
0&
#217
1"
1&
#218
0"
0&
#219
1"
1&
#220
0"
0&
#221
1"
1&
#222
0"
0&
#223
1"
1&
#224
0"
0&
#225
1"
1&
#226
0"
0&
#227
1"
1&
#228
0"
0&
#229
1"
1&
#230
0"
0&
#231
1"
1&
#232
0"
0&
#233
1"
1&
#234
0"
0&
#235
1"
1&
#236
0"
0&
#237
1"
1&
#238
0"
0&
#239
1"
1&
#240
0"
0&
#241
1"
1&
#242
0"
0&
#243
1"
1&
#244
0"
0&
#245
1"
1&
#246
0"
0&
#247
1"
1&
#248
0"
0&
#249
1"
1&
#250
0"
0&
#251
1"
1&
#252
0"
0&
#253
1"
1&
#254
0"
0&
#255
1"
1&
#256
0"
0&
#257
1"
1&
#258
0"
0&
#259
1"
1&
#260
0#
1$
0"
0&
1(
#261
1"
1&
#262
0"
0&
#263
1"
1&
#264
0"
0&
#265
1"
1&
#266
0"
0&
#267
1"
1&
#268
0"
0&
#269
1"
1&
#270
0"
0&
#271
1"
1&
#272
0"
0&
#273
1"
1&
#274
0"
0&
#275
1"
1&
#276
0"
0&
#277
1"
1&
#278
0"
0&
#279
1"
1&
#280
0"
0&
#281
1"
1&
#282
0"
0&
#283
1"
1&
#284
0"
0&
#285
1"
1&
#286
0"
0&
#287
1"
1&
#288
0"
0&
#289
1"
1&
#290
0"
0&
#291
1"
1&
#292
0"
0&
#293
1"
1&
#294
0"
0&
#295
1"
1&
#296
0"
0&
#297
1"
1&
#298
0"
0&
#299
1"
1&
#300
0"
0&
#301
1"
1&
#302
0"
0&
#303
1"
1&
#304
0"
0&
#305
1"
1&
#306
0"
0&
#307
1"
1&
#308
0"
0&
#309
1"
1&
#310
0"
0&
#311
1"
1&
#312
0"
0&
#313
1"
1&
#314
0"
0&
#315
0+
1%
1"
1&
1'
#316
0"
0&
#317
1"
1&
#318
0"
0&
#319
1"
1&
#320
0"
0&
#321
1"
1&
#322
0"
0&
#323
1"
1&
#324
0"
0&
#325
1"
1&
#326
0"
0&
#327
1"
1&
#328
0"
0&
#329
1"
1&
#330
0"
0&
#331
1"
1&
#332
0"
0&
#333
1"
1&
#334
0"
0&
#335
1"
1&
#336
0"
0&
#337
1"
1&
#338
0"
0&
#339
1"
1&
#340
0"
0&
#341
1"
1&
#342
0"
0&
#343
1"
1&
#344
0"
0&
#345
1"
1&
#346
0"
0&
#347
1"
1&
#348
0"
0&
#349
1"
1&
#350
0"
0&
#351
1"
1&
#352
0"
0&
#353
1"
1&
#354
0"
0&
#355
1"
1&
#356
0"
0&
#357
1"
1&
#358
0"
0&
#359
1"
1&
#360
0"
0&
#361
1"
1&
#362
0"
0&
#363
1"
1&
#364
0"
0&
#365
1"
1&
#366
0"
0&
#367
1"
1&
#368
0"
0&
#369
1"
1&
#370
0"
0&
#371
1"
1&
#372
0"
0&
#373
1"
1&
#374
0"
0&
#375
1"
1&
