fpga/twi_slave.v
// Prescaler that slows down the incoming clock by a specified value
module twi_slave (
		// Outside I/Os
		input scl,
		input sdaIn,
		output reg sdaOut = 1'b0,
		output reg sdaOutEn = 1'b0,

		// Internal wiring
		input [7:0] dataOut,
		output reg [7:0] dataIn
	);
	parameter ADDR = 7'h11;

	// State registers
	reg hasValidStartBit = 1'b0;
	reg hasValidStopBit = 1'b0;
	
	reg[2:0] state  = 3'b0;
	localparam STATE_WAITING_FOR_START_BIT  = 3'b000;
	localparam STATE_READING_ADDR 		= 3'b001;
	localparam STATE_WRITING_ACK 		= 3'b010;
	localparam STATE_READING_ACK 		= 3'b011;
	localparam STATE_READ_DATA		= 3'b100;
	localparam STATE_WRITE_DATA		= 3'b101;
	reg[2:0] bitCounter = 3'd0;
	reg masterRead = 1'b0;

	reg[7:0] dataToWrite = 0; // Latched copy of data to write
	reg[7:0] dataRead = 0; // Data (WIP)

	// Start & Stop bits:
	// "The address and the data bytes are sent most significant bit
	// first. The start bit is indicated by a high-to-low transition of
	// SDA with SCL high; the stop bit is indicated by a low-to-high
	// transition of SDA with SCL high. All other transitions of SDA take
	// place with SCL low."
	always @ (negedge sdaIn) hasValidStartBit <= scl;
	always @ (posedge sdaIn) hasValidStopBit <= scl;

	// Address & Data transmission: (Read happens on pos edge)
	// "Transmitting a data bit consists of pulsing the clock line high
	// while holding the data line steady at the desired level.
	always @ (posedge scl) begin
	  if (hasValidStopBit || state == STATE_WAITING_FOR_START_BIT) begin
            if (hasValidStartBit && sdaIn == ADDR[6]) 
		{state, bitCounter} <= {STATE_READING_ADDR, 3'd1};
	    else
		state <= STATE_WAITING_FOR_START_BIT;
          end
	  else if (state == STATE_READING_ADDR) begin
	  	// Only proceed if addr matches (MSB first)
	    	if (bitCounter == 3'b111) begin
	       		state <= STATE_WRITING_ACK;
			masterRead <= sdaIn;
			bitCounter <= 0;
	        end
	    	else if (sdaIn != ADDR[6 - bitCounter]) // Not our addr
	       		state <= STATE_WAITING_FOR_START_BIT;
            	else 
			bitCounter <= bitCounter + 1;
          end
	  else if (state == STATE_WRITING_ACK) begin
	 	{state, bitCounter} <= {masterRead ? STATE_WRITE_DATA : STATE_READ_DATA, 3'd0};
		dataToWrite <= dataOut;
	  end
          else if (state == STATE_READING_ACK)
	 	{state, bitCounter} <= {sdaIn ? STATE_WAITING_FOR_START_BIT : STATE_WRITE_DATA, 3'd0};
	  else if (state == STATE_READ_DATA) begin
		dataRead[7 - bitCounter] <= sdaIn;
		if (bitCounter == 3'b111) begin
			state <= STATE_WRITING_ACK;
			dataIn <= {dataRead[7:1], sdaIn};
		end
         	else
			bitCounter <= bitCounter + 1;
          end
	  else if (state == STATE_WRITE_DATA) begin
		if (bitCounter == 3'b111)
			state <= STATE_READING_ACK;
		else
         		bitCounter <= bitCounter + 1;
          end
	  else
		state <= STATE_WAITING_FOR_START_BIT;
        end
	
	// Write happens on negative edge
	always @ (negedge scl) begin
	  if (state == STATE_WRITING_ACK)
	  	{sdaOutEn, sdaOut} <= 2'b10;
	  else if (state == STATE_WRITE_DATA)
		{sdaOutEn, sdaOut} <= {1'b1, dataToWrite[7 - bitCounter]};
	  else
		{sdaOutEn, sdaOut} <= 2'b0Z;
	end
endmodule

fpga/twi_slave_tb.v
module twi_slave_tb();
  reg scl = 1'b1;
  reg sdaIn = 1'b1;
  wire sdaOut;  
  wire sdaOutEn;
  wire effectiveSda = sdaOutEn ? sdaOut : sdaIn;

  parameter ADDR = 7'b0111000;
  twi_slave #(.ADDR(ADDR)) INST(
	  .scl(scl),
	  .sdaIn(effectiveSda),
	  .sdaOut(sdaOut),
	  .sdaOutEn(sdaOutEn),
	  .dataOut(8'b10101010)
  );

  initial begin
	  $dumpfile("twi_slave_tb.vcd");
	  $dumpvars();

	  #10;

	  // Start bit
	  sdaIn = 0;

	  // Addr
	  #2 scl = 0; #1 sdaIn = ADDR[6]; #1 scl = 1;
	  #2 scl = 0; #1 sdaIn = ADDR[5]; #1 scl = 1;
	  #2 scl = 0; #1 sdaIn = ADDR[4]; #1 scl = 1;
	  #2 scl = 0; #1 sdaIn = ADDR[3]; #1 scl = 1;
	  #2 scl = 0; #1 sdaIn = ADDR[2]; #1 scl = 1;
	  #2 scl = 0; #1 sdaIn = ADDR[1]; #1 scl = 1;
	  #2 scl = 0; #1 sdaIn = ADDR[0]; #1 scl = 1;
	  #2 scl = 0; #1 sdaIn = 1 /* Req Data */; #1 scl = 1;

	  // Wait for Ack
	  #2 scl = 0; #2 scl = 1;

	  // See response 
	  #2 scl = 0; #10 scl = 1;
	  #2 scl = 0; #2 scl = 1;
	  #2 scl = 0; #2 scl = 1;
	  #2 scl = 0; #2 scl = 1;
	  #2 scl = 0; #2 scl = 1;
	  #2 scl = 0; #2 scl = 1;
	  #2 scl = 0; #2 scl = 1;
	  #2 scl = 0; #2 scl = 1; // NACK
	  #2 scl = 0; #2 scl = 1;
	  #2 scl = 0; #2 scl = 1;
	  #2 scl = 0; #2 scl = 1;
	  #2 scl = 0; #2 scl = 1;

	  #10 $finish;
  end
endmodule

fpga/twi_slave_tb.vcd
$date
	Sun Jan 20 18:32:07 2019
$end
$version
	Icarus Verilog
$end
$timescale
	1s
$end
$scope module twi_slave_tb $end
$var wire 1 ! sdaOutEn $end
$var wire 1 " sdaOut $end
$var wire 1 # effectiveSda $end
$var reg 1 $ scl $end
$var reg 1 % sdaIn $end
$scope module INST $end
$var wire 8 & dataOut [7:0] $end
$var wire 1 $ scl $end
$var wire 1 # sdaIn $end
$var reg 3 ' bitCounter [2:0] $end
$var reg 8 ( dataIn [7:0] $end
$var reg 8 ) dataRead [7:0] $end
$var reg 8 * dataToWrite [7:0] $end
$var reg 1 + hasValidStartBit $end
$var reg 1 , hasValidStopBit $end
$var reg 1 - masterRead $end
$var reg 1 " sdaOut $end
$var reg 1 ! sdaOutEn $end
$var reg 3 . state [2:0] $end
$upscope $end
$upscope $end
$enddefinitions $end
#0
$dumpvars
b0 .
0-
1,
0+
b0 *
b0 )
bx (
b0 '
b10101010 &
1%
1$
1#
0"
0!
$end
#10
1+
0#
0%
#12
z"
0$
#14
b1 .
b1 '
1$
#16
0$
#17
0,
1#
1%
#18
b10 '
1$
#20
0$
#22
b11 '
1$
#24
0$
#26
b100 '
1$
#28
0$
#29
0+
0#
0%
#30
b101 '
1$
#32
0$
#34
b110 '
1$
#36
0$
#38
b111 '
1$
#40
0$
#41
1#
1%
#42
b0 '
1-
b10 .
1$
#44
0#
1!
0"
0$
#46
b10101010 *
b0 (
b101 .
1$
#48
1#
1"
0$
#58
b1 '
1$
#60
0#
0"
0$
#62
b10 '
1$
#64
1#
1"
0$
#66
b11 '
1$
#68
0#
0"
0$
#70
b100 '
1$
#72
1#
1"
0$
#74
b101 '
1$
#76
0#
0"
0$
#78
b110 '
1$
#80
1#
1"
0$
#82
b111 '
1$
#84
0#
0"
0$
#86
b11 .
1$
#88
1#
0!
z"
0$
#90
b0 .
b0 '
1$
#92
0$
#94
1$
#96
0$
#98
1$
#100
0$
#102
1$
