fpga/uart_tx_tb.v
module uart_tx_tb();
	reg clk = 1'b0;
	wire tx, eol;

	reg[7:0] num = 8'hA5;

	uart_tx_stream #(.N(32), .WAIT(20)) INST (
		.clk(clk),
		.tx(tx),
		.eol(eol),
		.dataStream({"Hello World: ", uart_format.hex8(num) , "\n"})
		//.dataStream({"Hello", "World: \n"})

	);

	always #1 clk <= ~clk;

	initial begin
		$dumpfile("uart_tx_tb.vcd");
		$dumpvars;
		#2000 $finish;
	end
endmodule

fpga/uart_tx.v
`ifdef TESTBENCH
module uart_format();
`endif
  function [8:1] hex;
    input[4:1] in;
    hex = in < 10 ? ("0" + in) : ( "A" + (in - 10)); 
  endfunction

  function [32:1] hex8;
    input[8:1] in;
    hex8 = {"0x", hex(in[8:5]), hex(in[4:1])};
  endfunction

  function [48:1] hex16;
    input[16:1] in;
    hex8 = {"0x", hex(in[16:13]), hex(in[12:9]), hex(in[8:5]), hex(in[4:1])};
  endfunction
`ifdef TESTBENCH
endmodule
`endif

module uart_tx_stream(
	input clk,
	output wire tx,
	output eol,
	input[(8*N)-1:0] dataStream
);
	parameter N = 32;
	parameter WIDTH = $clog2(N);
	parameter WAIT = 30;
	parameter WIDTH_WAIT = $clog2(WAIT);

	wire nextWord;
	wire[7:0] word;
	reg[WIDTH:1] counter = 0;
	wire hold;
	uart_tx UART_INST (.clk(clk), .tx(tx), .nextWord(nextWord), .wordIn(word), .hold(hold));

	reg[WIDTH_WAIT:1] holdCounter = 0;

	assign eol = counter >= N;
	assign word =  dataStream >> 8*(N-1-counter);
	always @ (posedge nextWord) begin
		if (eol) counter <= 0;
		else counter <= counter + 1;
	end
	always @ (posedge clk) begin
		if (holdCounter > 0) holdCounter <= holdCounter - 1;
		else if (eol) holdCounter <= WAIT;
	end
	assign hold = holdCounter > 0;
endmodule

module uart_tx( // no parity, 1 stop bit
	input clk,
	input hold,
	output tx,
	output nextWord,
	input[7:0] wordIn
);
	parameter STOP_BITS = 1;

	localparam STATE_STOP_BIT	= 2'b00;
	localparam STATE_START_BIT 	= 2'b01;
	localparam STATE_DATA 		= 2'b10;
	reg[1:0]  state = STATE_STOP_BIT;

	reg[7:0] bufferedPacket;
	reg[2:0] dataCounter = 3'd0;

	reg txState = 1'b1;
	assign tx = bufferedPacket == 8'h0 ? 1'b1 : txState;

	assign nextWord = (state == STATE_STOP_BIT);

	always @* case (state)
		default: txState <= 1'b1;
		STATE_START_BIT: txState <= 1'b0;
		STATE_DATA: txState <= bufferedPacket[dataCounter];
		STATE_STOP_BIT: txState <= 1'b1;
	endcase
	
	always @ (posedge clk) begin
		casez (state)
			STATE_STOP_BIT:
				if (dataCounter > 0)
					dataCounter <= dataCounter - 1;
				else if (!hold) 
					{state, bufferedPacket} <= {STATE_START_BIT, wordIn};
			STATE_START_BIT: {state, dataCounter} <= {STATE_DATA, 3'd0};
			STATE_DATA:
				if (dataCounter == 3'b111)
					{state, dataCounter} <= {STATE_STOP_BIT, STOP_BITS - 3'd1};
				else
					dataCounter <= dataCounter + 3'd1;

		endcase
	end
endmodule

fpga/uart_tx_tb.vcd
$date
	Wed Jan 23 22:18:23 2019
$end
$version
	Icarus Verilog
$end
$timescale
	1s
$end
$scope module uart_format $end
$scope function hex $end
$var reg 8 ! hex [8:1] $end
$var reg 4 " in [4:1] $end
$upscope $end
$scope function hex8 $end
$var reg 32 # hex8 [32:1] $end
$var reg 8 $ in [8:1] $end
$upscope $end
$upscope $end
$scope module uart_tx_tb $end
$var wire 1 % tx $end
$var wire 1 & eol $end
$var reg 1 ' clk $end
$var reg 8 ( num [7:0] $end
$scope module INST $end
$var wire 1 ' clk $end
$var wire 256 ) dataStream [255:0] $end
$var wire 8 * word [7:0] $end
$var wire 1 % tx $end
$var wire 1 + nextWord $end
$var wire 1 , hold $end
$var wire 1 & eol $end
$var reg 5 - counter [5:1] $end
$var reg 5 . holdCounter [5:1] $end
$scope module UART_INST $end
$var wire 1 ' clk $end
$var wire 1 , hold $end
$var wire 8 / wordIn [7:0] $end
$var wire 1 % tx $end
$var wire 1 + nextWord $end
$var reg 8 0 bufferedPacket [7:0] $end
$var reg 3 1 dataCounter [2:0] $end
$var reg 2 2 state [1:0] $end
$var reg 1 3 txState $end
$upscope $end
$upscope $end
$upscope $end
$enddefinitions $end
#0
$dumpvars
13
b0 2
b0 1
bx 0
b0 /
b0 .
b0 -
0,
1+
b0 *
b10010000110010101101100011011000110111100100000010101110110111101110010011011000110010000111010001000000011000001111000010000010011010100001010 )
b10100101 (
0'
0&
1%
b10100101 $
b110000011110000100000100110101 #
b101 "
b110101 !
$end
#1
03
0+
b1 2
b0 0
1'
#2
0'
#3
b10 2
1'
#4
0'
#5
b1 1
1'
#6
0'
#7
b10 1
1'
#8
0'
#9
b11 1
1'
#10
0'
#11
b100 1
1'
#12
0'
#13
b101 1
1'
#14
0'
#15
b110 1
1'
#16
0'
#17
b111 1
1'
#18
0'
#19
b1 -
13
1+
b0 2
b0 1
1'
#20
0'
#21
03
0+
b1 2
1'
#22
0'
#23
b10 2
1'
#24
0'
#25
b1 1
1'
#26
0'
#27
b10 1
1'
#28
0'
#29
b11 1
1'
#30
0'
#31
b100 1
1'
#32
0'
#33
b101 1
1'
#34
0'
#35
b110 1
1'
#36
0'
#37
b111 1
1'
#38
0'
#39
b10 -
13
1+
b0 2
b0 1
1'
#40
0'
#41
03
0+
b1 2
1'
#42
0'
#43
b10 2
1'
#44
0'
#45
b1 1
1'
#46
0'
#47
b10 1
1'
#48
0'
#49
b11 1
1'
#50
0'
#51
b100 1
1'
#52
0'
#53
b101 1
1'
#54
0'
#55
b110 1
1'
#56
0'
#57
b111 1
1'
#58
0'
#59
b11 -
13
1+
b0 2
b0 1
1'
#60
0'
#61
03
0+
b1 2
1'
#62
0'
#63
b10 2
1'
#64
0'
#65
b1 1
1'
#66
0'
#67
b10 1
1'
#68
0'
#69
b11 1
1'
#70
0'
#71
b100 1
1'
#72
0'
#73
b101 1
1'
#74
0'
#75
b110 1
1'
#76
0'
#77
b111 1
1'
#78
0'
#79
b100 -
13
1+
b0 2
b0 1
1'
#80
0'
#81
03
0+
b1 2
1'
#82
0'
#83
b10 2
1'
#84
0'
#85
b1 1
1'
#86
0'
#87
b10 1
1'
#88
0'
#89
b11 1
1'
#90
0'
#91
b100 1
1'
#92
0'
#93
b101 1
1'
#94
0'
#95
b110 1
1'
#96
0'
#97
b111 1
1'
#98
0'
#99
b101 -
13
1+
b0 2
b0 1
1'
#100
0'
#101
03
0+
b1 2
1'
#102
0'
#103
b10 2
1'
#104
0'
#105
b1 1
1'
#106
0'
#107
b10 1
1'
#108
0'
#109
b11 1
1'
#110
0'
#111
b100 1
1'
#112
0'
#113
b101 1
1'
#114
0'
#115
b110 1
1'
#116
0'
#117
b111 1
1'
#118
0'
#119
b110 -
13
1+
b0 2
b0 1
1'
#120
0'
#121
03
0+
b1 2
1'
#122
0'
#123
b10 2
1'
#124
0'
#125
b1 1
1'
#126
0'
#127
b10 1
1'
#128
0'
#129
b11 1
1'
#130
0'
#131
b100 1
1'
#132
0'
#133
b101 1
1'
#134
0'
#135
b110 1
1'
#136
0'
#137
b111 1
1'
#138
0'
#139
b111 -
13
1+
b0 2
b0 1
1'
#140
0'
#141
03
0+
b1 2
1'
#142
0'
#143
b10 2
1'
#144
0'
#145
b1 1
1'
#146
0'
#147
b10 1
1'
#148
0'
#149
b11 1
1'
#150
0'
#151
b100 1
1'
#152
0'
#153
b101 1
1'
#154
0'
#155
b110 1
1'
#156
0'
#157
b111 1
1'
#158
0'
#159
b1000 -
13
1+
b0 2
b0 1
1'
#160
0'
#161
03
0+
b1 2
1'
#162
0'
#163
b10 2
1'
#164
0'
#165
b1 1
1'
#166
0'
#167
b10 1
1'
#168
0'
#169
b11 1
1'
#170
0'
#171
b100 1
1'
#172
0'
#173
b101 1
1'
#174
0'
#175
b110 1
1'
#176
0'
#177
b111 1
1'
#178
0'
#179
b1001 -
13
1+
b0 2
b0 1
1'
#180
0'
#181
03
0+
b1 2
1'
#182
0'
#183
b10 2
1'
#184
0'
#185
b1 1
1'
#186
0'
#187
b10 1
1'
#188
0'
#189
b11 1
1'
#190
0'
#191
b100 1
1'
#192
0'
#193
b101 1
1'
#194
0'
#195
b110 1
1'
#196
0'
#197
b111 1
1'
#198
0'
#199
b1010 -
13
1+
b0 2
b0 1
1'
#200
0'
#201
03
0+
b1 2
1'
#202
0'
#203
b10 2
1'
#204
0'
#205
b1 1
1'
#206
0'
#207
b10 1
1'
#208
0'
#209
b11 1
1'
#210
0'
#211
b100 1
1'
#212
0'
#213
b101 1
1'
#214
0'
#215
b110 1
1'
#216
0'
#217
b111 1
1'
#218
0'
#219
b1011 -
13
1+
b0 2
b0 1
1'
#220
0'
#221
03
0+
b1 2
1'
#222
0'
#223
b10 2
1'
#224
0'
#225
b1 1
1'
#226
0'
#227
b10 1
1'
#228
0'
#229
b11 1
1'
#230
0'
#231
b100 1
1'
#232
0'
#233
b101 1
1'
#234
0'
#235
b110 1
1'
#236
0'
#237
b111 1
1'
#238
0'
#239
b1100 -
13
1+
b0 2
b0 1
1'
#240
0'
#241
03
0+
b1 2
1'
#242
0'
#243
b10 2
1'
#244
0'
#245
b1 1
1'
#246
0'
#247
b10 1
1'
#248
0'
#249
b11 1
1'
#250
0'
#251
b100 1
1'
#252
0'
#253
b101 1
1'
#254
0'
#255
b110 1
1'
#256
0'
#257
b111 1
1'
#258
0'
#259
b1101 -
13
1+
b0 2
b0 1
1'
#260
0'
#261
03
0+
b1 2
1'
#262
0'
#263
b10 2
1'
#264
0'
#265
b1 1
1'
#266
0'
#267
b10 1
1'
#268
0'
#269
b11 1
1'
#270
0'
#271
b100 1
1'
#272
0'
#273
b101 1
1'
#274
0'
#275
b110 1
1'
#276
0'
#277
b111 1
1'
#278
0'
#279
b1001000 *
b1001000 /
b1110 -
13
1+
b0 2
b0 1
1'
#280
0'
#281
0%
03
0+
b1 2
b1001000 0
1'
#282
0'
#283
b10 2
1'
#284
0'
#285
b1 1
1'
#286
0'
#287
b10 1
1'
#288
0'
#289
1%
13
b11 1
1'
#290
0'
#291
0%
03
b100 1
1'
#292
0'
#293
b101 1
1'
#294
0'
#295
1%
13
b110 1
1'
#296
0'
#297
0%
03
b111 1
1'
#298
0'
#299
b1100101 *
b1100101 /
1%
b1111 -
13
1+
b0 2
b0 1
1'
#300
0'
#301
0%
03
0+
b1 2
b1100101 0
1'
#302
0'
#303
1%
13
b10 2
1'
#304
0'
#305
0%
03
b1 1
1'
#306
0'
#307
1%
13
b10 1
1'
#308
0'
#309
0%
03
b11 1
1'
#310
0'
#311
b100 1
1'
#312
0'
#313
1%
13
b101 1
1'
#314
0'
#315
b110 1
1'
#316
0'
#317
0%
03
b111 1
1'
#318
0'
#319
b1101100 *
b1101100 /
1%
b10000 -
13
1+
b0 2
b0 1
1'
#320
0'
#321
0%
03
0+
b1 2
b1101100 0
1'
#322
0'
#323
b10 2
1'
#324
0'
#325
b1 1
1'
#326
0'
#327
1%
13
b10 1
1'
#328
0'
#329
b11 1
1'
#330
0'
#331
0%
03
b100 1
1'
#332
0'
#333
1%
13
b101 1
1'
#334
0'
#335
b110 1
1'
#336
0'
#337
0%
03
b111 1
1'
#338
0'
#339
1%
b10001 -
13
1+
b0 2
b0 1
1'
#340
0'
#341
0%
03
0+
b1 2
1'
#342
0'
#343
b10 2
1'
#344
0'
#345
b1 1
1'
#346
0'
#347
1%
13
b10 1
1'
#348
0'
#349
b11 1
1'
#350
0'
#351
0%
03
b100 1
1'
#352
0'
#353
1%
13
b101 1
1'
#354
0'
#355
b110 1
1'
#356
0'
#357
0%
03
b111 1
1'
#358
0'
#359
b1101111 *
b1101111 /
1%
b10010 -
13
1+
b0 2
b0 1
1'
#360
0'
#361
0%
03
0+
b1 2
b1101111 0
1'
#362
0'
#363
1%
13
b10 2
1'
#364
0'
#365
b1 1
1'
#366
0'
#367
b10 1
1'
#368
0'
#369
b11 1
1'
#370
0'
#371
0%
03
b100 1
1'
#372
0'
#373
1%
13
b101 1
1'
#374
0'
#375
b110 1
1'
#376
0'
#377
0%
03
b111 1
1'
#378
0'
#379
b100000 *
b100000 /
1%
b10011 -
13
1+
b0 2
b0 1
1'
#380
0'
#381
0%
03
0+
b1 2
b100000 0
1'
#382
0'
#383
b10 2
1'
#384
0'
#385
b1 1
1'
#386
0'
#387
b10 1
1'
#388
0'
#389
b11 1
1'
#390
0'
#391
b100 1
1'
#392
0'
#393
1%
13
b101 1
1'
#394
0'
#395
0%
03
b110 1
1'
#396
0'
#397
b111 1
1'
#398
0'
#399
b1010111 *
b1010111 /
1%
b10100 -
13
1+
b0 2
b0 1
1'
#400
0'
#401
0%
03
0+
b1 2
b1010111 0
1'
#402
0'
#403
1%
13
b10 2
1'
#404
0'
#405
b1 1
1'
#406
0'
#407
b10 1
1'
#408
0'
#409
0%
03
b11 1
1'
#410
0'
#411
1%
13
b100 1
1'
#412
0'
#413
0%
03
b101 1
1'
#414
0'
#415
1%
13
b110 1
1'
#416
0'
#417
0%
03
b111 1
1'
#418
0'
#419
b1101111 *
b1101111 /
1%
b10101 -
13
1+
b0 2
b0 1
1'
#420
0'
#421
0%
03
0+
b1 2
b1101111 0
1'
#422
0'
#423
1%
13
b10 2
1'
#424
0'
#425
b1 1
1'
#426
0'
#427
b10 1
1'
#428
0'
#429
b11 1
1'
#430
0'
#431
0%
03
b100 1
1'
#432
0'
#433
1%
13
b101 1
1'
#434
0'
#435
b110 1
1'
#436
0'
#437
0%
03
b111 1
1'
#438
0'
#439
b1110010 *
b1110010 /
1%
b10110 -
13
1+
b0 2
b0 1
1'
#440
0'
#441
0%
03
0+
b1 2
b1110010 0
1'
#442
0'
#443
b10 2
1'
#444
0'
#445
1%
13
b1 1
1'
#446
0'
#447
0%
03
b10 1
1'
#448
0'
#449
b11 1
1'
#450
0'
#451
1%
13
b100 1
1'
#452
0'
#453
b101 1
1'
#454
0'
#455
b110 1
1'
#456
0'
#457
0%
03
b111 1
1'
#458
0'
#459
b1101100 *
b1101100 /
1%
b10111 -
13
1+
b0 2
b0 1
1'
#460
0'
#461
0%
03
0+
b1 2
b1101100 0
1'
#462
0'
#463
b10 2
1'
#464
0'
#465
b1 1
1'
#466
0'
#467
1%
13
b10 1
1'
#468
0'
#469
b11 1
1'
#470
0'
#471
0%
03
b100 1
1'
#472
0'
#473
1%
13
b101 1
1'
#474
0'
#475
b110 1
1'
#476
0'
#477
0%
03
b111 1
1'
#478
0'
#479
b1100100 *
b1100100 /
1%
b11000 -
13
1+
b0 2
b0 1
1'
#480
0'
#481
0%
03
0+
b1 2
b1100100 0
1'
#482
0'
#483
b10 2
1'
#484
0'
#485
b1 1
1'
#486
0'
#487
1%
13
b10 1
1'
#488
0'
#489
0%
03
b11 1
1'
#490
0'
#491
b100 1
1'
#492
0'
#493
1%
13
b101 1
1'
#494
0'
#495
b110 1
1'
#496
0'
#497
0%
03
b111 1
1'
#498
0'
#499
b111010 *
b111010 /
1%
b11001 -
13
1+
b0 2
b0 1
1'
#500
0'
#501
0%
03
0+
b1 2
b111010 0
1'
#502
0'
#503
b10 2
1'
#504
0'
#505
1%
13
b1 1
1'
#506
0'
#507
0%
03
b10 1
1'
#508
0'
#509
1%
13
b11 1
1'
#510
0'
#511
b100 1
1'
#512
0'
#513
b101 1
1'
#514
0'
#515
0%
03
b110 1
1'
#516
0'
#517
b111 1
1'
#518
0'
#519
b100000 *
b100000 /
1%
b11010 -
13
1+
b0 2
b0 1
1'
#520
0'
#521
0%
03
0+
b1 2
b100000 0
1'
#522
0'
#523
b10 2
1'
#524
0'
#525
b1 1
1'
#526
0'
#527
b10 1
1'
#528
0'
#529
b11 1
1'
#530
0'
#531
b100 1
1'
#532
0'
#533
1%
13
b101 1
1'
#534
0'
#535
0%
03
b110 1
1'
#536
0'
#537
b111 1
1'
#538
0'
#539
b110000 *
b110000 /
1%
b11011 -
13
1+
b0 2
b0 1
1'
#540
0'
#541
0%
03
0+
b1 2
b110000 0
1'
#542
0'
#543
b10 2
1'
#544
0'
#545
b1 1
1'
#546
0'
#547
b10 1
1'
#548
0'
#549
b11 1
1'
#550
0'
#551
1%
13
b100 1
1'
#552
0'
#553
b101 1
1'
#554
0'
#555
0%
03
b110 1
1'
#556
0'
#557
b111 1
1'
#558
0'
#559
b1111000 *
b1111000 /
1%
b11100 -
13
1+
b0 2
b0 1
1'
#560
0'
#561
0%
03
0+
b1 2
b1111000 0
1'
#562
0'
#563
b10 2
1'
#564
0'
#565
b1 1
1'
#566
0'
#567
b10 1
1'
#568
0'
#569
1%
13
b11 1
1'
#570
0'
#571
b100 1
1'
#572
0'
#573
b101 1
1'
#574
0'
#575
b110 1
1'
#576
0'
#577
0%
03
b111 1
1'
#578
0'
#579
b1000001 *
b1000001 /
1%
b11101 -
13
1+
b0 2
b0 1
1'
#580
0'
#581
0%
03
0+
b1 2
b1000001 0
1'
#582
0'
#583
1%
13
b10 2
1'
#584
0'
#585
0%
03
b1 1
1'
#586
0'
#587
b10 1
1'
#588
0'
#589
b11 1
1'
#590
0'
#591
b100 1
1'
#592
0'
#593
b101 1
1'
#594
0'
#595
1%
13
b110 1
1'
#596
0'
#597
0%
03
b111 1
1'
#598
0'
#599
b110101 *
b110101 /
1%
b11110 -
13
1+
b0 2
b0 1
1'
#600
0'
#601
0%
03
0+
b1 2
b110101 0
1'
#602
0'
#603
1%
13
b10 2
1'
#604
0'
#605
0%
03
b1 1
1'
#606
0'
#607
1%
13
b10 1
1'
#608
0'
#609
0%
03
b11 1
1'
#610
0'
#611
1%
13
b100 1
1'
#612
0'
#613
b101 1
1'
#614
0'
#615
0%
03
b110 1
1'
#616
0'
#617
b111 1
1'
#618
0'
#619
b1010 *
b1010 /
1%
b11111 -
13
1+
b0 2
b0 1
1'
#620
0'
#621
0%
03
0+
b1 2
b1010 0
1'
#622
0'
#623
b10 2
1'
#624
0'
#625
1%
13
b1 1
1'
#626
0'
#627
0%
03
b10 1
1'
#628
0'
#629
1%
13
b11 1
1'
#630
0'
#631
0%
03
b100 1
1'
#632
0'
#633
b101 1
1'
#634
0'
#635
b110 1
1'
#636
0'
#637
b111 1
1'
#638
0'
#639
b0 *
b0 /
1%
b0 -
13
1+
b0 2
b0 1
1'
#640
0'
#641
03
0+
b1 2
b0 0
1'
#642
0'
#643
b10 2
1'
#644
0'
#645
b1 1
1'
#646
0'
#647
b10 1
1'
#648
0'
#649
b11 1
1'
#650
0'
#651
b100 1
1'
#652
0'
#653
b101 1
1'
#654
0'
#655
b110 1
1'
#656
0'
#657
b111 1
1'
#658
0'
#659
b1 -
13
1+
b0 2
b0 1
1'
#660
0'
#661
03
0+
b1 2
1'
#662
0'
#663
b10 2
1'
#664
0'
#665
b1 1
1'
#666
0'
#667
b10 1
1'
#668
0'
#669
b11 1
1'
#670
0'
#671
b100 1
1'
#672
0'
#673
b101 1
1'
#674
0'
#675
b110 1
1'
#676
0'
#677
b111 1
1'
#678
0'
#679
b10 -
13
1+
b0 2
b0 1
1'
#680
0'
#681
03
0+
b1 2
1'
#682
0'
#683
b10 2
1'
#684
0'
#685
b1 1
1'
#686
0'
#687
b10 1
1'
#688
0'
#689
b11 1
1'
#690
0'
#691
b100 1
1'
#692
0'
#693
b101 1
1'
#694
0'
#695
b110 1
1'
#696
0'
#697
b111 1
1'
#698
0'
#699
b11 -
13
1+
b0 2
b0 1
1'
#700
0'
#701
03
0+
b1 2
1'
#702
0'
#703
b10 2
1'
#704
0'
#705
b1 1
1'
#706
0'
#707
b10 1
1'
#708
0'
#709
b11 1
1'
#710
0'
#711
b100 1
1'
#712
0'
#713
b101 1
1'
#714
0'
#715
b110 1
1'
#716
0'
#717
b111 1
1'
#718
0'
#719
b100 -
13
1+
b0 2
b0 1
1'
#720
0'
#721
03
0+
b1 2
1'
#722
0'
#723
b10 2
1'
#724
0'
#725
b1 1
1'
#726
0'
#727
b10 1
1'
#728
0'
#729
b11 1
1'
#730
0'
#731
b100 1
1'
#732
0'
#733
b101 1
1'
#734
0'
#735
b110 1
1'
#736
0'
#737
b111 1
1'
#738
0'
#739
b101 -
13
1+
b0 2
b0 1
1'
#740
0'
#741
03
0+
b1 2
1'
#742
0'
#743
b10 2
1'
#744
0'
#745
b1 1
1'
#746
0'
#747
b10 1
1'
#748
0'
#749
b11 1
1'
#750
0'
#751
b100 1
1'
#752
0'
#753
b101 1
1'
#754
0'
#755
b110 1
1'
#756
0'
#757
b111 1
1'
#758
0'
#759
b110 -
13
1+
b0 2
b0 1
1'
#760
0'
#761
03
0+
b1 2
1'
#762
0'
#763
b10 2
1'
#764
0'
#765
b1 1
1'
#766
0'
#767
b10 1
1'
#768
0'
#769
b11 1
1'
#770
0'
#771
b100 1
1'
#772
0'
#773
b101 1
1'
#774
0'
#775
b110 1
1'
#776
0'
#777
b111 1
1'
#778
0'
#779
b111 -
13
1+
b0 2
b0 1
1'
#780
0'
#781
03
0+
b1 2
1'
#782
0'
#783
b10 2
1'
#784
0'
#785
b1 1
1'
#786
0'
#787
b10 1
1'
#788
0'
#789
b11 1
1'
#790
0'
#791
b100 1
1'
#792
0'
#793
b101 1
1'
#794
0'
#795
b110 1
1'
#796
0'
#797
b111 1
1'
#798
0'
#799
b1000 -
13
1+
b0 2
b0 1
1'
#800
0'
#801
03
0+
b1 2
1'
#802
0'
#803
b10 2
1'
#804
0'
#805
b1 1
1'
#806
0'
#807
b10 1
1'
#808
0'
#809
b11 1
1'
#810
0'
#811
b100 1
1'
#812
0'
#813
b101 1
1'
#814
0'
#815
b110 1
1'
#816
0'
#817
b111 1
1'
#818
0'
#819
b1001 -
13
1+
b0 2
b0 1
1'
#820
0'
#821
03
0+
b1 2
1'
#822
0'
#823
b10 2
1'
#824
0'
#825
b1 1
1'
#826
0'
#827
b10 1
1'
#828
0'
#829
b11 1
1'
#830
0'
#831
b100 1
1'
#832
0'
#833
b101 1
1'
#834
0'
#835
b110 1
1'
#836
0'
#837
b111 1
1'
#838
0'
#839
b1010 -
13
1+
b0 2
b0 1
1'
#840
0'
#841
03
0+
b1 2
1'
#842
0'
#843
b10 2
1'
#844
0'
#845
b1 1
1'
#846
0'
#847
b10 1
1'
#848
0'
#849
b11 1
1'
#850
0'
#851
b100 1
1'
#852
0'
#853
b101 1
1'
#854
0'
#855
b110 1
1'
#856
0'
#857
b111 1
1'
#858
0'
#859
b1011 -
13
1+
b0 2
b0 1
1'
#860
0'
#861
03
0+
b1 2
1'
#862
0'
#863
b10 2
1'
#864
0'
#865
b1 1
1'
#866
0'
#867
b10 1
1'
#868
0'
#869
b11 1
1'
#870
0'
#871
b100 1
1'
#872
0'
#873
b101 1
1'
#874
0'
#875
b110 1
1'
#876
0'
#877
b111 1
1'
#878
0'
#879
b1100 -
13
1+
b0 2
b0 1
1'
#880
0'
#881
03
0+
b1 2
1'
#882
0'
#883
b10 2
1'
#884
0'
#885
b1 1
1'
#886
0'
#887
b10 1
1'
#888
0'
#889
b11 1
1'
#890
0'
#891
b100 1
1'
#892
0'
#893
b101 1
1'
#894
0'
#895
b110 1
1'
#896
0'
#897
b111 1
1'
#898
0'
#899
b1101 -
13
1+
b0 2
b0 1
1'
#900
0'
#901
03
0+
b1 2
1'
#902
0'
#903
b10 2
1'
#904
0'
#905
b1 1
1'
#906
0'
#907
b10 1
1'
#908
0'
#909
b11 1
1'
#910
0'
#911
b100 1
1'
#912
0'
#913
b101 1
1'
#914
0'
#915
b110 1
1'
#916
0'
#917
b111 1
1'
#918
0'
#919
b1001000 *
b1001000 /
b1110 -
13
1+
b0 2
b0 1
1'
#920
0'
#921
0%
03
0+
b1 2
b1001000 0
1'
#922
0'
#923
b10 2
1'
#924
0'
#925
b1 1
1'
#926
0'
#927
b10 1
1'
#928
0'
#929
1%
13
b11 1
1'
#930
0'
#931
0%
03
b100 1
1'
#932
0'
#933
b101 1
1'
#934
0'
#935
1%
13
b110 1
1'
#936
0'
#937
0%
03
b111 1
1'
#938
0'
#939
b1100101 *
b1100101 /
1%
b1111 -
13
1+
b0 2
b0 1
1'
#940
0'
#941
0%
03
0+
b1 2
b1100101 0
1'
#942
0'
#943
1%
13
b10 2
1'
#944
0'
#945
0%
03
b1 1
1'
#946
0'
#947
1%
13
b10 1
1'
#948
0'
#949
0%
03
b11 1
1'
#950
0'
#951
b100 1
1'
#952
0'
#953
1%
13
b101 1
1'
#954
0'
#955
b110 1
1'
#956
0'
#957
0%
03
b111 1
1'
#958
0'
#959
b1101100 *
b1101100 /
1%
b10000 -
13
1+
b0 2
b0 1
1'
#960
0'
#961
0%
03
0+
b1 2
b1101100 0
1'
#962
0'
#963
b10 2
1'
#964
0'
#965
b1 1
1'
#966
0'
#967
1%
13
b10 1
1'
#968
0'
#969
b11 1
1'
#970
0'
#971
0%
03
b100 1
1'
#972
0'
#973
1%
13
b101 1
1'
#974
0'
#975
b110 1
1'
#976
0'
#977
0%
03
b111 1
1'
#978
0'
#979
1%
b10001 -
13
1+
b0 2
b0 1
1'
#980
0'
#981
0%
03
0+
b1 2
1'
#982
0'
#983
b10 2
1'
#984
0'
#985
b1 1
1'
#986
0'
#987
1%
13
b10 1
1'
#988
0'
#989
b11 1
1'
#990
0'
#991
0%
03
b100 1
1'
#992
0'
#993
1%
13
b101 1
1'
#994
0'
#995
b110 1
1'
#996
0'
#997
0%
03
b111 1
1'
#998
0'
#999
b1101111 *
b1101111 /
1%
b10010 -
13
1+
b0 2
b0 1
1'
#1000
0'
#1001
0%
03
0+
b1 2
b1101111 0
1'
#1002
0'
#1003
1%
13
b10 2
1'
#1004
0'
#1005
b1 1
1'
#1006
0'
#1007
b10 1
1'
#1008
0'
#1009
b11 1
1'
#1010
0'
#1011
0%
03
b100 1
1'
#1012
0'
#1013
1%
13
b101 1
1'
#1014
0'
#1015
b110 1
1'
#1016
0'
#1017
0%
03
b111 1
1'
#1018
0'
#1019
b100000 *
b100000 /
1%
b10011 -
13
1+
b0 2
b0 1
1'
#1020
0'
#1021
0%
03
0+
b1 2
b100000 0
1'
#1022
0'
#1023
b10 2
1'
#1024
0'
#1025
b1 1
1'
#1026
0'
#1027
b10 1
1'
#1028
0'
#1029
b11 1
1'
#1030
0'
#1031
b100 1
1'
#1032
0'
#1033
1%
13
b101 1
1'
#1034
0'
#1035
0%
03
b110 1
1'
#1036
0'
#1037
b111 1
1'
#1038
0'
#1039
b1010111 *
b1010111 /
1%
b10100 -
13
1+
b0 2
b0 1
1'
#1040
0'
#1041
0%
03
0+
b1 2
b1010111 0
1'
#1042
0'
#1043
1%
13
b10 2
1'
#1044
0'
#1045
b1 1
1'
#1046
0'
#1047
b10 1
1'
#1048
0'
#1049
0%
03
b11 1
1'
#1050
0'
#1051
1%
13
b100 1
1'
#1052
0'
#1053
0%
03
b101 1
1'
#1054
0'
#1055
1%
13
b110 1
1'
#1056
0'
#1057
0%
03
b111 1
1'
#1058
0'
#1059
b1101111 *
b1101111 /
1%
b10101 -
13
1+
b0 2
b0 1
1'
#1060
0'
#1061
0%
03
0+
b1 2
b1101111 0
1'
#1062
0'
#1063
1%
13
b10 2
1'
#1064
0'
#1065
b1 1
1'
#1066
0'
#1067
b10 1
1'
#1068
0'
#1069
b11 1
1'
#1070
0'
#1071
0%
03
b100 1
1'
#1072
0'
#1073
1%
13
b101 1
1'
#1074
0'
#1075
b110 1
1'
#1076
0'
#1077
0%
03
b111 1
1'
#1078
0'
#1079
b1110010 *
b1110010 /
1%
b10110 -
13
1+
b0 2
b0 1
1'
#1080
0'
#1081
0%
03
0+
b1 2
b1110010 0
1'
#1082
0'
#1083
b10 2
1'
#1084
0'
#1085
1%
13
b1 1
1'
#1086
0'
#1087
0%
03
b10 1
1'
#1088
0'
#1089
b11 1
1'
#1090
0'
#1091
1%
13
b100 1
1'
#1092
0'
#1093
b101 1
1'
#1094
0'
#1095
b110 1
1'
#1096
0'
#1097
0%
03
b111 1
1'
#1098
0'
#1099
b1101100 *
b1101100 /
1%
b10111 -
13
1+
b0 2
b0 1
1'
#1100
0'
#1101
0%
03
0+
b1 2
b1101100 0
1'
#1102
0'
#1103
b10 2
1'
#1104
0'
#1105
b1 1
1'
#1106
0'
#1107
1%
13
b10 1
1'
#1108
0'
#1109
b11 1
1'
#1110
0'
#1111
0%
03
b100 1
1'
#1112
0'
#1113
1%
13
b101 1
1'
#1114
0'
#1115
b110 1
1'
#1116
0'
#1117
0%
03
b111 1
1'
#1118
0'
#1119
b1100100 *
b1100100 /
1%
b11000 -
13
1+
b0 2
b0 1
1'
#1120
0'
#1121
0%
03
0+
b1 2
b1100100 0
1'
#1122
0'
#1123
b10 2
1'
#1124
0'
#1125
b1 1
1'
#1126
0'
#1127
1%
13
b10 1
1'
#1128
0'
#1129
0%
03
b11 1
1'
#1130
0'
#1131
b100 1
1'
#1132
0'
#1133
1%
13
b101 1
1'
#1134
0'
#1135
b110 1
1'
#1136
0'
#1137
0%
03
b111 1
1'
#1138
0'
#1139
b111010 *
b111010 /
1%
b11001 -
13
1+
b0 2
b0 1
1'
#1140
0'
#1141
0%
03
0+
b1 2
b111010 0
1'
#1142
0'
#1143
b10 2
1'
#1144
0'
#1145
1%
13
b1 1
1'
#1146
0'
#1147
0%
03
b10 1
1'
#1148
0'
#1149
1%
13
b11 1
1'
#1150
0'
#1151
b100 1
1'
#1152
0'
#1153
b101 1
1'
#1154
0'
#1155
0%
03
b110 1
1'
#1156
0'
#1157
b111 1
1'
#1158
0'
#1159
b100000 *
b100000 /
1%
b11010 -
13
1+
b0 2
b0 1
1'
#1160
0'
#1161
0%
03
0+
b1 2
b100000 0
1'
#1162
0'
#1163
b10 2
1'
#1164
0'
#1165
b1 1
1'
#1166
0'
